pyunity/__init__.pyi
pyunity/audio.pyi
pyunity/config.pyi
pyunity/core.pyi
pyunity/errors.pyi
pyunity/files.pyi
pyunity/gui.pyi
pyunity/input.pyi
pyunity/loader.pyi
pyunity/logger.pyi
pyunity/meshes.pyi
pyunity/render.pyi
pyunity/settings.pyi
pyunity/examples/__init__.pyi
pyunity/physics/__init__.pyi
pyunity/physics/config.pyi
pyunity/physics/core.pyi
pyunity/scenes/__init__.pyi
pyunity/scenes/scene.pyi
pyunity/scenes/sceneManager.pyi
pyunity/values/__init__.pyi
pyunity/values/abc.pyi
pyunity/values/other.pyi
pyunity/values/quaternion.pyi
pyunity/values/texture.pyi
pyunity/values/vector.pyi
pyunity/window/__init__.pyi
pyunity_stubs-0.8.3.post2.dist-info/METADATA
pyunity_stubs-0.8.3.post2.dist-info/WHEEL
pyunity_stubs-0.8.3.post2.dist-info/top_level.txt
pyunity_stubs-0.8.3.post2.dist-info/RECORD
